jb_misc_lib/__init__.py
jb_misc_lib/core.py
jb_misc_lib/object.py
jb_misc_lib/text_ui.py
jb_misc_lib/typesafe.py
jb_misc_lib-0.1.4.dist-info/LICENSE
jb_misc_lib-0.1.4.dist-info/METADATA
jb_misc_lib-0.1.4.dist-info/WHEEL
jb_misc_lib-0.1.4.dist-info/top_level.txt
jb_misc_lib-0.1.4.dist-info/RECORD
